pycrux/__init__.py
pycrux/crux.py
pycrux/pipes.py
pycrux/utils/__init__.py
pycrux/utils/config.py
pycrux/utils/logger.py
pycrux-0.7.0.dist-info/LICENSE
pycrux-0.7.0.dist-info/METADATA
pycrux-0.7.0.dist-info/WHEEL
pycrux-0.7.0.dist-info/RECORD
