Metadata-Version: 2.1
Name: pycrux
Version: 0.7.0
Summary: A python wrapper for crFitTool.
Home-page: https://github.com/WahooFitness/pycrux
Author: Thomas Camminady
Author-email: 0milieux_member@icloud.com
Requires-Python: >=3.9,<3.12
Classifier: Programming Language :: Python :: 3
Classifier: Programming Language :: Python :: 3.9
Classifier: Programming Language :: Python :: 3.10
Classifier: Programming Language :: Python :: 3.11
Requires-Dist: polars (>=0.20.26,<0.21.0)
